{
  "metadata": {
    "preset": "checkered",
    "deck": "checkered"
  },
  "events": [
    {
      "ante": 1,
      "blind_type": null,
      "event_type": "run_start",
      "data": {
        "starting_money": 4,
        "starting_jokers": [],
        "starting_hand_levels": {}
      },
      "timestamp": 0
    },
    {
      "ante": 1,
      "blind_type": "SMALL",
      "event_type": "blind_result",
      "data": {
        "score": 376,
        "required": 300,
        "success": true,
        "margin": 76,
        "margin_pct": 25.3,
        "hands_used": 2,
        "discards_used": 1,
        "best_hand": "FLUSH",
        "close_call": false
      },
      "timestamp": 1
    },
    {
      "ante": 1,
      "blind_type": null,
      "event_type": "joker_acquired",
      "data": {
        "joker": "To Do List",
        "source": "shop"
      },
      "timestamp": 2
    },
    {
      "ante": 1,
      "blind_type": null,
      "event_type": "hand_level_up",
      "data": {
        "planet": "Neptune",
        "hand_type": "STRAIGHT_FLUSH",
        "new_level": 2
      },
      "timestamp": 3
    },
    {
      "ante": 1,
      "blind_type": null,
      "event_type": "shop_visit",
      "data": {
        "jokers_bought": [
          "To Do List"
        ],
        "planets_used": [
          "Neptune"
        ],
        "money_spent": 7,
        "money_remaining": 0
      },
      "timestamp": 4
    },
    {
      "ante": 1,
      "blind_type": "BIG",
      "event_type": "blind_result",
      "data": {
        "score": 672,
        "required": 450,
        "success": true,
        "margin": 222,
        "margin_pct": 49.3,
        "hands_used": 3,
        "discards_used": 3,
        "best_hand": "FULL_HOUSE",
        "close_call": false
      },
      "timestamp": 5
    },
    {
      "ante": 1,
      "blind_type": null,
      "event_type": "joker_acquired",
      "data": {
        "joker": "Abstract Joker",
        "source": "shop"
      },
      "timestamp": 6
    },
    {
      "ante": 1,
      "blind_type": null,
      "event_type": "shop_visit",
      "data": {
        "jokers_bought": [
          "Abstract Joker"
        ],
        "planets_used": [],
        "money_spent": 4,
        "money_remaining": 0
      },
      "timestamp": 7
    },
    {
      "ante": 1,
      "blind_type": "BOSS",
      "event_type": "blind_result",
      "data": {
        "score": 747,
        "required": 600,
        "success": true,
        "margin": 147,
        "margin_pct": 24.5,
        "hands_used": 2,
        "discards_used": 2,
        "best_hand": "FLUSH",
        "close_call": false,
        "boss_name": "The House"
      },
      "timestamp": 8
    },
    {
      "ante": 1,
      "blind_type": null,
      "event_type": "joker_acquired",
      "data": {
        "joker": "Photograph",
        "source": "shop"
      },
      "timestamp": 9
    },
    {
      "ante": 1,
      "blind_type": null,
      "event_type": "shop_visit",
      "data": {
        "jokers_bought": [
          "Photograph"
        ],
        "planets_used": [],
        "money_spent": 5,
        "money_remaining": 0
      },
      "timestamp": 10
    },
    {
      "ante": 2,
      "blind_type": "SMALL",
      "event_type": "blind_result",
      "data": {
        "score": 860,
        "required": 800,
        "success": true,
        "margin": 60,
        "margin_pct": 7.5,
        "hands_used": 2,
        "discards_used": 2,
        "best_hand": "THREE_OF_A_KIND",
        "close_call": true
      },
      "timestamp": 11
    },
    {
      "ante": 2,
      "blind_type": null,
      "event_type": "hand_level_up",
      "data": {
        "planet": "Neptune",
        "hand_type": "STRAIGHT_FLUSH",
        "new_level": 3
      },
      "timestamp": 12
    },
    {
      "ante": 2,
      "blind_type": null,
      "event_type": "shop_visit",
      "data": {
        "jokers_bought": [],
        "planets_used": [
          "Neptune"
        ],
        "money_spent": 3,
        "money_remaining": 0
      },
      "timestamp": 13
    },
    {
      "ante": 2,
      "blind_type": "BIG",
      "event_type": "blind_result",
      "data": {
        "score": 1618,
        "required": 1200,
        "success": true,
        "margin": 418,
        "margin_pct": 34.8,
        "hands_used": 2,
        "discards_used": 2,
        "best_hand": "STRAIGHT",
        "close_call": false
      },
      "timestamp": 14
    },
    {
      "ante": 2,
      "blind_type": null,
      "event_type": "shop_visit",
      "data": {
        "jokers_bought": [],
        "planets_used": [],
        "money_spent": 0,
        "money_remaining": 4
      },
      "timestamp": 15
    },
    {
      "ante": 2,
      "blind_type": "BOSS",
      "event_type": "blind_result",
      "data": {
        "score": 2624,
        "required": 1600,
        "success": true,
        "margin": 1024,
        "margin_pct": 64.0,
        "hands_used": 3,
        "discards_used": 2,
        "best_hand": "FULL_HOUSE",
        "close_call": false,
        "boss_name": "The Arm"
      },
      "timestamp": 16
    },
    {
      "ante": 2,
      "blind_type": null,
      "event_type": "joker_acquired",
      "data": {
        "joker": "Scary Face",
        "source": "shop"
      },
      "timestamp": 17
    },
    {
      "ante": 2,
      "blind_type": null,
      "event_type": "joker_acquired",
      "data": {
        "joker": "Runner",
        "source": "shop"
      },
      "timestamp": 18
    },
    {
      "ante": 2,
      "blind_type": null,
      "event_type": "shop_visit",
      "data": {
        "jokers_bought": [
          "Scary Face",
          "Runner"
        ],
        "planets_used": [],
        "money_spent": 9,
        "money_remaining": 0
      },
      "timestamp": 19
    },
    {
      "ante": 3,
      "blind_type": "SMALL",
      "event_type": "blind_result",
      "data": {
        "score": 2393,
        "required": 2000,
        "success": true,
        "margin": 393,
        "margin_pct": 19.7,
        "hands_used": 3,
        "discards_used": 3,
        "best_hand": "FLUSH",
        "close_call": true
      },
      "timestamp": 20
    },
    {
      "ante": 3,
      "blind_type": null,
      "event_type": "hand_level_up",
      "data": {
        "planet": "Saturn",
        "hand_type": "STRAIGHT",
        "new_level": 2
      },
      "timestamp": 21
    },
    {
      "ante": 3,
      "blind_type": null,
      "event_type": "shop_visit",
      "data": {
        "jokers_bought": [],
        "planets_used": [
          "Saturn"
        ],
        "money_spent": 3,
        "money_remaining": 0
      },
      "timestamp": 22
    },
    {
      "ante": 3,
      "blind_type": "BIG",
      "event_type": "blind_result",
      "data": {
        "score": 3580,
        "required": 3000,
        "success": true,
        "margin": 580,
        "margin_pct": 19.3,
        "hands_used": 2,
        "discards_used": 2,
        "best_hand": "STRAIGHT",
        "close_call": true
      },
      "timestamp": 23
    },
    {
      "ante": 3,
      "blind_type": null,
      "event_type": "shop_visit",
      "data": {
        "jokers_bought": [],
        "planets_used": [],
        "money_spent": 0,
        "money_remaining": 4
      },
      "timestamp": 24
    },
    {
      "ante": 3,
      "blind_type": "BOSS",
      "event_type": "blind_result",
      "data": {
        "score": 3190,
        "required": 4000,
        "success": false,
        "margin": -810,
        "margin_pct": -20.2,
        "hands_used": 4,
        "discards_used": 2,
        "best_hand": "STRAIGHT",
        "close_call": false,
        "boss_name": "The Wheel"
      },
      "timestamp": 25
    },
    {
      "ante": 3,
      "blind_type": "BOSS",
      "event_type": "run_end",
      "data": {
        "victory": false,
        "blinds_beaten": 8,
        "final_money": 4,
        "final_jokers": [
          "To Do List",
          "Abstract Joker",
          "Photograph",
          "Scary Face",
          "Runner"
        ],
        "final_hand_levels": {
          "STRAIGHT": 2,
          "STRAIGHT_FLUSH": 3
        }
      },
      "timestamp": 26
    }
  ],
  "summary": {
    "total_blinds_attempted": 9,
    "blinds_won": 8,
    "close_calls": 3,
    "jokers_acquired": 5,
    "planets_used": 3,
    "victory": false
  }
}