{
  "metadata": {
    "preset": "standard",
    "deck": "standard"
  },
  "events": [
    {
      "ante": 1,
      "blind_type": null,
      "event_type": "run_start",
      "data": {
        "starting_money": 4,
        "starting_jokers": [],
        "starting_hand_levels": {}
      },
      "timestamp": 0
    },
    {
      "ante": 1,
      "blind_type": "SMALL",
      "event_type": "blind_result",
      "data": {
        "score": 304,
        "required": 300,
        "success": true,
        "margin": 4,
        "margin_pct": 1.3,
        "hands_used": 1,
        "discards_used": 1,
        "best_hand": "FLUSH",
        "close_call": true
      },
      "timestamp": 1
    },
    {
      "ante": 1,
      "blind_type": null,
      "event_type": "joker_acquired",
      "data": {
        "joker": "Mystic Summit",
        "source": "shop"
      },
      "timestamp": 2
    },
    {
      "ante": 1,
      "blind_type": null,
      "event_type": "shop_visit",
      "data": {
        "jokers_bought": [
          "Mystic Summit"
        ],
        "planets_used": [],
        "money_spent": 5,
        "money_remaining": 2
      },
      "timestamp": 3
    },
    {
      "ante": 1,
      "blind_type": "BIG",
      "event_type": "blind_result",
      "data": {
        "score": 714,
        "required": 450,
        "success": true,
        "margin": 264,
        "margin_pct": 58.7,
        "hands_used": 2,
        "discards_used": 0,
        "best_hand": "PAIR",
        "close_call": false
      },
      "timestamp": 4
    },
    {
      "ante": 1,
      "blind_type": null,
      "event_type": "joker_acquired",
      "data": {
        "joker": "Square Joker",
        "source": "shop"
      },
      "timestamp": 5
    },
    {
      "ante": 1,
      "blind_type": null,
      "event_type": "shop_visit",
      "data": {
        "jokers_bought": [
          "Square Joker"
        ],
        "planets_used": [],
        "money_spent": 4,
        "money_remaining": 2
      },
      "timestamp": 6
    },
    {
      "ante": 1,
      "blind_type": "BOSS",
      "event_type": "blind_result",
      "data": {
        "score": 1710,
        "required": 600,
        "success": true,
        "margin": 1110,
        "margin_pct": 185.0,
        "hands_used": 1,
        "discards_used": 0,
        "best_hand": "FULL_HOUSE",
        "close_call": false,
        "boss_name": "The Ox"
      },
      "timestamp": 7
    },
    {
      "ante": 1,
      "blind_type": null,
      "event_type": "joker_acquired",
      "data": {
        "joker": "Crafty Joker",
        "source": "shop"
      },
      "timestamp": 8
    },
    {
      "ante": 1,
      "blind_type": null,
      "event_type": "hand_level_up",
      "data": {
        "planet": "Earth",
        "hand_type": "FULL_HOUSE",
        "new_level": 2
      },
      "timestamp": 9
    },
    {
      "ante": 1,
      "blind_type": null,
      "event_type": "shop_visit",
      "data": {
        "jokers_bought": [
          "Crafty Joker"
        ],
        "planets_used": [
          "Earth"
        ],
        "money_spent": 7,
        "money_remaining": 0
      },
      "timestamp": 10
    },
    {
      "ante": 2,
      "blind_type": "SMALL",
      "event_type": "blind_result",
      "data": {
        "score": 810,
        "required": 800,
        "success": true,
        "margin": 10,
        "margin_pct": 1.2,
        "hands_used": 1,
        "discards_used": 0,
        "best_hand": "THREE_OF_A_KIND",
        "close_call": true
      },
      "timestamp": 11
    },
    {
      "ante": 2,
      "blind_type": null,
      "event_type": "shop_visit",
      "data": {
        "jokers_bought": [],
        "planets_used": [],
        "money_spent": 0,
        "money_remaining": 3
      },
      "timestamp": 12
    },
    {
      "ante": 2,
      "blind_type": "BIG",
      "event_type": "blind_result",
      "data": {
        "score": 1700,
        "required": 1200,
        "success": true,
        "margin": 500,
        "margin_pct": 41.7,
        "hands_used": 2,
        "discards_used": 1,
        "best_hand": "TWO_PAIR",
        "close_call": false
      },
      "timestamp": 13
    },
    {
      "ante": 2,
      "blind_type": null,
      "event_type": "joker_acquired",
      "data": {
        "joker": "Gluttonous Joker",
        "source": "shop"
      },
      "timestamp": 14
    },
    {
      "ante": 2,
      "blind_type": null,
      "event_type": "shop_visit",
      "data": {
        "jokers_bought": [
          "Gluttonous Joker"
        ],
        "planets_used": [],
        "money_spent": 5,
        "money_remaining": 2
      },
      "timestamp": 15
    },
    {
      "ante": 2,
      "blind_type": "BOSS",
      "event_type": "blind_result",
      "data": {
        "score": 4072,
        "required": 2400,
        "success": true,
        "margin": 1672,
        "margin_pct": 69.7,
        "hands_used": 2,
        "discards_used": 1,
        "best_hand": "FULL_HOUSE",
        "close_call": false,
        "boss_name": "The Wall"
      },
      "timestamp": 16
    },
    {
      "ante": 2,
      "blind_type": null,
      "event_type": "joker_acquired",
      "data": {
        "joker": "Photograph",
        "source": "shop"
      },
      "timestamp": 17
    },
    {
      "ante": 2,
      "blind_type": null,
      "event_type": "shop_visit",
      "data": {
        "jokers_bought": [
          "Photograph"
        ],
        "planets_used": [],
        "money_spent": 5,
        "money_remaining": 2
      },
      "timestamp": 18
    },
    {
      "ante": 3,
      "blind_type": "SMALL",
      "event_type": "blind_result",
      "data": {
        "score": 7426,
        "required": 2000,
        "success": true,
        "margin": 5426,
        "margin_pct": 271.3,
        "hands_used": 2,
        "discards_used": 0,
        "best_hand": "FULL_HOUSE",
        "close_call": false
      },
      "timestamp": 19
    },
    {
      "ante": 3,
      "blind_type": null,
      "event_type": "hand_level_up",
      "data": {
        "planet": "Planet X",
        "hand_type": "FIVE_OF_A_KIND",
        "new_level": 2
      },
      "timestamp": 20
    },
    {
      "ante": 3,
      "blind_type": null,
      "event_type": "shop_visit",
      "data": {
        "jokers_bought": [],
        "planets_used": [
          "Planet X"
        ],
        "money_spent": 3,
        "money_remaining": 2
      },
      "timestamp": 21
    },
    {
      "ante": 3,
      "blind_type": "BIG",
      "event_type": "blind_result",
      "data": {
        "score": 3920,
        "required": 3000,
        "success": true,
        "margin": 920,
        "margin_pct": 30.7,
        "hands_used": 2,
        "discards_used": 1,
        "best_hand": "TWO_PAIR",
        "close_call": false
      },
      "timestamp": 22
    },
    {
      "ante": 3,
      "blind_type": null,
      "event_type": "hand_level_up",
      "data": {
        "planet": "Ceres",
        "hand_type": "FLUSH_HOUSE",
        "new_level": 2
      },
      "timestamp": 23
    },
    {
      "ante": 3,
      "blind_type": null,
      "event_type": "hand_level_up",
      "data": {
        "planet": "Neptune",
        "hand_type": "STRAIGHT_FLUSH",
        "new_level": 2
      },
      "timestamp": 24
    },
    {
      "ante": 3,
      "blind_type": null,
      "event_type": "shop_visit",
      "data": {
        "jokers_bought": [],
        "planets_used": [
          "Ceres",
          "Neptune"
        ],
        "money_spent": 6,
        "money_remaining": 0
      },
      "timestamp": 25
    },
    {
      "ante": 3,
      "blind_type": "BOSS",
      "event_type": "blind_result",
      "data": {
        "score": 6566,
        "required": 4000,
        "success": true,
        "margin": 2566,
        "margin_pct": 64.1,
        "hands_used": 2,
        "discards_used": 1,
        "best_hand": "STRAIGHT",
        "close_call": false,
        "boss_name": "The House"
      },
      "timestamp": 26
    },
    {
      "ante": 3,
      "blind_type": null,
      "event_type": "hand_level_up",
      "data": {
        "planet": "Earth",
        "hand_type": "FULL_HOUSE",
        "new_level": 3
      },
      "timestamp": 27
    },
    {
      "ante": 3,
      "blind_type": null,
      "event_type": "shop_visit",
      "data": {
        "jokers_bought": [],
        "planets_used": [
          "Earth"
        ],
        "money_spent": 3,
        "money_remaining": 2
      },
      "timestamp": 28
    },
    {
      "ante": 4,
      "blind_type": "SMALL",
      "event_type": "blind_result",
      "data": {
        "score": 6359,
        "required": 5000,
        "success": true,
        "margin": 1359,
        "margin_pct": 27.2,
        "hands_used": 2,
        "discards_used": 1,
        "best_hand": "STRAIGHT",
        "close_call": false
      },
      "timestamp": 29
    },
    {
      "ante": 4,
      "blind_type": null,
      "event_type": "hand_level_up",
      "data": {
        "planet": "Earth",
        "hand_type": "FULL_HOUSE",
        "new_level": 4
      },
      "timestamp": 30
    },
    {
      "ante": 4,
      "blind_type": null,
      "event_type": "shop_visit",
      "data": {
        "jokers_bought": [],
        "planets_used": [
          "Earth"
        ],
        "money_spent": 3,
        "money_remaining": 2
      },
      "timestamp": 31
    },
    {
      "ante": 4,
      "blind_type": "BIG",
      "event_type": "blind_result",
      "data": {
        "score": 13180,
        "required": 7500,
        "success": true,
        "margin": 5680,
        "margin_pct": 75.7,
        "hands_used": 3,
        "discards_used": 3,
        "best_hand": "FLUSH",
        "close_call": false
      },
      "timestamp": 32
    },
    {
      "ante": 4,
      "blind_type": null,
      "event_type": "hand_level_up",
      "data": {
        "planet": "Mars",
        "hand_type": "FOUR_OF_A_KIND",
        "new_level": 2
      },
      "timestamp": 33
    },
    {
      "ante": 4,
      "blind_type": null,
      "event_type": "shop_visit",
      "data": {
        "jokers_bought": [],
        "planets_used": [
          "Mars"
        ],
        "money_spent": 3,
        "money_remaining": 3
      },
      "timestamp": 34
    },
    {
      "ante": 4,
      "blind_type": "BOSS",
      "event_type": "blind_result",
      "data": {
        "score": 7060,
        "required": 10000,
        "success": false,
        "margin": -2940,
        "margin_pct": -29.4,
        "hands_used": 4,
        "discards_used": 3,
        "best_hand": "TWO_PAIR",
        "close_call": false,
        "boss_name": "The Water"
      },
      "timestamp": 35
    },
    {
      "ante": 4,
      "blind_type": "BOSS",
      "event_type": "run_end",
      "data": {
        "victory": false,
        "blinds_beaten": 11,
        "final_money": 3,
        "final_jokers": [
          "Mystic Summit",
          "Square Joker",
          "Crafty Joker",
          "Gluttonous Joker",
          "Photograph"
        ],
        "final_hand_levels": {
          "FULL_HOUSE": 4,
          "FOUR_OF_A_KIND": 2,
          "STRAIGHT_FLUSH": 2,
          "FIVE_OF_A_KIND": 2,
          "FLUSH_HOUSE": 2
        }
      },
      "timestamp": 36
    }
  ],
  "summary": {
    "total_blinds_attempted": 12,
    "blinds_won": 11,
    "close_calls": 2,
    "jokers_acquired": 5,
    "planets_used": 7,
    "victory": false
  }
}