{
  "metadata": {
    "preset": "painted",
    "deck": "painted"
  },
  "events": [
    {
      "ante": 1,
      "blind_type": null,
      "event_type": "run_start",
      "data": {
        "starting_money": 4,
        "starting_jokers": [],
        "starting_hand_levels": {}
      },
      "timestamp": 0
    },
    {
      "ante": 1,
      "blind_type": "SMALL",
      "event_type": "blind_result",
      "data": {
        "score": 400,
        "required": 300,
        "success": true,
        "margin": 100,
        "margin_pct": 33.3,
        "hands_used": 2,
        "discards_used": 0,
        "best_hand": "STRAIGHT",
        "close_call": false
      },
      "timestamp": 1
    },
    {
      "ante": 1,
      "blind_type": null,
      "event_type": "joker_acquired",
      "data": {
        "joker": "Golden Ticket",
        "source": "shop"
      },
      "timestamp": 2
    },
    {
      "ante": 1,
      "blind_type": null,
      "event_type": "shop_visit",
      "data": {
        "jokers_bought": [
          "Golden Ticket"
        ],
        "planets_used": [],
        "money_spent": 5,
        "money_remaining": 2
      },
      "timestamp": 3
    },
    {
      "ante": 1,
      "blind_type": "BIG",
      "event_type": "blind_result",
      "data": {
        "score": 612,
        "required": 450,
        "success": true,
        "margin": 162,
        "margin_pct": 36.0,
        "hands_used": 2,
        "discards_used": 1,
        "best_hand": "STRAIGHT",
        "close_call": false
      },
      "timestamp": 4
    },
    {
      "ante": 1,
      "blind_type": null,
      "event_type": "joker_acquired",
      "data": {
        "joker": "Red Card",
        "source": "shop"
      },
      "timestamp": 5
    },
    {
      "ante": 1,
      "blind_type": null,
      "event_type": "shop_visit",
      "data": {
        "jokers_bought": [
          "Red Card"
        ],
        "planets_used": [],
        "money_spent": 5,
        "money_remaining": 1
      },
      "timestamp": 6
    },
    {
      "ante": 1,
      "blind_type": "BOSS",
      "event_type": "blind_result",
      "data": {
        "score": 1196,
        "required": 600,
        "success": true,
        "margin": 596,
        "margin_pct": 99.3,
        "hands_used": 2,
        "discards_used": 0,
        "best_hand": "FULL_HOUSE",
        "close_call": false
      },
      "timestamp": 7
    },
    {
      "ante": 1,
      "blind_type": null,
      "event_type": "joker_acquired",
      "data": {
        "joker": "Square Joker",
        "source": "shop"
      },
      "timestamp": 8
    },
    {
      "ante": 1,
      "blind_type": null,
      "event_type": "shop_visit",
      "data": {
        "jokers_bought": [
          "Square Joker"
        ],
        "planets_used": [],
        "money_spent": 4,
        "money_remaining": 2
      },
      "timestamp": 9
    },
    {
      "ante": 2,
      "blind_type": "SMALL",
      "event_type": "blind_result",
      "data": {
        "score": 830,
        "required": 800,
        "success": true,
        "margin": 30,
        "margin_pct": 3.8,
        "hands_used": 1,
        "discards_used": 0,
        "best_hand": "STRAIGHT",
        "close_call": true
      },
      "timestamp": 10
    },
    {
      "ante": 2,
      "blind_type": null,
      "event_type": "joker_acquired",
      "data": {
        "joker": "Jolly Joker",
        "source": "shop"
      },
      "timestamp": 11
    },
    {
      "ante": 2,
      "blind_type": null,
      "event_type": "shop_visit",
      "data": {
        "jokers_bought": [
          "Jolly Joker"
        ],
        "planets_used": [],
        "money_spent": 3,
        "money_remaining": 2
      },
      "timestamp": 12
    },
    {
      "ante": 2,
      "blind_type": "BIG",
      "event_type": "blind_result",
      "data": {
        "score": 1798,
        "required": 1200,
        "success": true,
        "margin": 598,
        "margin_pct": 49.8,
        "hands_used": 2,
        "discards_used": 1,
        "best_hand": "TWO_PAIR",
        "close_call": false
      },
      "timestamp": 13
    },
    {
      "ante": 2,
      "blind_type": null,
      "event_type": "hand_level_up",
      "data": {
        "planet": "Eris",
        "hand_type": "FLUSH_FIVE",
        "new_level": 2
      },
      "timestamp": 14
    },
    {
      "ante": 2,
      "blind_type": null,
      "event_type": "shop_visit",
      "data": {
        "jokers_bought": [],
        "planets_used": [
          "Eris"
        ],
        "money_spent": 3,
        "money_remaining": 3
      },
      "timestamp": 15
    },
    {
      "ante": 2,
      "blind_type": "BOSS",
      "event_type": "blind_result",
      "data": {
        "score": 2048,
        "required": 1600,
        "success": true,
        "margin": 448,
        "margin_pct": 28.0,
        "hands_used": 2,
        "discards_used": 0,
        "best_hand": "TWO_PAIR",
        "close_call": false
      },
      "timestamp": 16
    },
    {
      "ante": 2,
      "blind_type": null,
      "event_type": "shop_visit",
      "data": {
        "jokers_bought": [],
        "planets_used": [],
        "money_spent": 0,
        "money_remaining": 8
      },
      "timestamp": 17
    },
    {
      "ante": 3,
      "blind_type": "SMALL",
      "event_type": "blind_result",
      "data": {
        "score": 3018,
        "required": 2000,
        "success": true,
        "margin": 1018,
        "margin_pct": 50.9,
        "hands_used": 3,
        "discards_used": 2,
        "best_hand": "TWO_PAIR",
        "close_call": false
      },
      "timestamp": 18
    },
    {
      "ante": 3,
      "blind_type": null,
      "event_type": "hand_level_up",
      "data": {
        "planet": "Pluto",
        "hand_type": "HIGH_CARD",
        "new_level": 2
      },
      "timestamp": 19
    },
    {
      "ante": 3,
      "blind_type": null,
      "event_type": "shop_visit",
      "data": {
        "jokers_bought": [],
        "planets_used": [
          "Pluto"
        ],
        "money_spent": 3,
        "money_remaining": 9
      },
      "timestamp": 20
    },
    {
      "ante": 3,
      "blind_type": "BIG",
      "event_type": "blind_result",
      "data": {
        "score": 3648,
        "required": 3000,
        "success": true,
        "margin": 648,
        "margin_pct": 21.6,
        "hands_used": 3,
        "discards_used": 3,
        "best_hand": "TWO_PAIR",
        "close_call": false
      },
      "timestamp": 21
    },
    {
      "ante": 3,
      "blind_type": null,
      "event_type": "hand_level_up",
      "data": {
        "planet": "Saturn",
        "hand_type": "STRAIGHT",
        "new_level": 2
      },
      "timestamp": 22
    },
    {
      "ante": 3,
      "blind_type": null,
      "event_type": "hand_level_up",
      "data": {
        "planet": "Mercury",
        "hand_type": "PAIR",
        "new_level": 2
      },
      "timestamp": 23
    },
    {
      "ante": 3,
      "blind_type": null,
      "event_type": "shop_visit",
      "data": {
        "jokers_bought": [],
        "planets_used": [
          "Saturn",
          "Mercury"
        ],
        "money_spent": 6,
        "money_remaining": 8
      },
      "timestamp": 24
    },
    {
      "ante": 3,
      "blind_type": "BOSS",
      "event_type": "blind_result",
      "data": {
        "score": 4685,
        "required": 4000,
        "success": true,
        "margin": 685,
        "margin_pct": 17.1,
        "hands_used": 3,
        "discards_used": 3,
        "best_hand": "STRAIGHT",
        "close_call": true
      },
      "timestamp": 25
    },
    {
      "ante": 3,
      "blind_type": null,
      "event_type": "shop_visit",
      "data": {
        "jokers_bought": [],
        "planets_used": [],
        "money_spent": 0,
        "money_remaining": 14
      },
      "timestamp": 26
    },
    {
      "ante": 4,
      "blind_type": "SMALL",
      "event_type": "blind_result",
      "data": {
        "score": 5644,
        "required": 5000,
        "success": true,
        "margin": 644,
        "margin_pct": 12.9,
        "hands_used": 4,
        "discards_used": 3,
        "best_hand": "TWO_PAIR",
        "close_call": true
      },
      "timestamp": 27
    },
    {
      "ante": 4,
      "blind_type": null,
      "event_type": "hand_level_up",
      "data": {
        "planet": "Mercury",
        "hand_type": "PAIR",
        "new_level": 3
      },
      "timestamp": 28
    },
    {
      "ante": 4,
      "blind_type": null,
      "event_type": "shop_visit",
      "data": {
        "jokers_bought": [],
        "planets_used": [
          "Mercury"
        ],
        "money_spent": 3,
        "money_remaining": 16
      },
      "timestamp": 29
    },
    {
      "ante": 4,
      "blind_type": "BIG",
      "event_type": "blind_result",
      "data": {
        "score": 6666,
        "required": 7500,
        "success": false,
        "margin": -834,
        "margin_pct": -11.1,
        "hands_used": 4,
        "discards_used": 3,
        "best_hand": "TWO_PAIR",
        "close_call": true
      },
      "timestamp": 30
    },
    {
      "ante": 4,
      "blind_type": "BIG",
      "event_type": "run_end",
      "data": {
        "victory": false,
        "blinds_beaten": 10,
        "final_money": 16,
        "final_jokers": [
          "Golden Ticket",
          "Red Card",
          "Square Joker",
          "Jolly Joker"
        ],
        "final_hand_levels": {
          "HIGH_CARD": 2,
          "PAIR": 3,
          "STRAIGHT": 2,
          "FLUSH_FIVE": 2
        }
      },
      "timestamp": 31
    }
  ],
  "summary": {
    "total_blinds_attempted": 11,
    "blinds_won": 10,
    "close_calls": 4,
    "jokers_acquired": 4,
    "planets_used": 5,
    "victory": false
  }
}