{
  "metadata": {
    "preset": "red",
    "deck": "red"
  },
  "events": [
    {
      "ante": 1,
      "blind_type": null,
      "event_type": "run_start",
      "data": {
        "starting_money": 4,
        "starting_jokers": [],
        "starting_hand_levels": {}
      },
      "timestamp": 0
    },
    {
      "ante": 1,
      "blind_type": "SMALL",
      "event_type": "blind_result",
      "data": {
        "score": 336,
        "required": 300,
        "success": true,
        "margin": 36,
        "margin_pct": 12.0,
        "hands_used": 2,
        "discards_used": 2,
        "best_hand": "STRAIGHT",
        "close_call": true
      },
      "timestamp": 1
    },
    {
      "ante": 1,
      "blind_type": null,
      "event_type": "joker_acquired",
      "data": {
        "joker": "Golden Ticket",
        "source": "shop"
      },
      "timestamp": 2
    },
    {
      "ante": 1,
      "blind_type": null,
      "event_type": "shop_visit",
      "data": {
        "jokers_bought": [
          "Golden Ticket"
        ],
        "planets_used": [],
        "money_spent": 5,
        "money_remaining": 2
      },
      "timestamp": 3
    },
    {
      "ante": 1,
      "blind_type": "BIG",
      "event_type": "blind_result",
      "data": {
        "score": 699,
        "required": 450,
        "success": true,
        "margin": 249,
        "margin_pct": 55.3,
        "hands_used": 4,
        "discards_used": 3,
        "best_hand": "STRAIGHT",
        "close_call": false
      },
      "timestamp": 4
    },
    {
      "ante": 1,
      "blind_type": null,
      "event_type": "joker_acquired",
      "data": {
        "joker": "Abstract Joker",
        "source": "shop"
      },
      "timestamp": 5
    },
    {
      "ante": 1,
      "blind_type": null,
      "event_type": "shop_visit",
      "data": {
        "jokers_bought": [
          "Abstract Joker"
        ],
        "planets_used": [],
        "money_spent": 4,
        "money_remaining": 2
      },
      "timestamp": 6
    },
    {
      "ante": 1,
      "blind_type": "BOSS",
      "event_type": "blind_result",
      "data": {
        "score": 647,
        "required": 600,
        "success": true,
        "margin": 47,
        "margin_pct": 7.8,
        "hands_used": 2,
        "discards_used": 1,
        "best_hand": "STRAIGHT",
        "close_call": true,
        "boss_name": "The House"
      },
      "timestamp": 7
    },
    {
      "ante": 1,
      "blind_type": null,
      "event_type": "joker_acquired",
      "data": {
        "joker": "Shoot the Moon",
        "source": "shop"
      },
      "timestamp": 8
    },
    {
      "ante": 1,
      "blind_type": null,
      "event_type": "shop_visit",
      "data": {
        "jokers_bought": [
          "Shoot the Moon"
        ],
        "planets_used": [],
        "money_spent": 5,
        "money_remaining": 2
      },
      "timestamp": 9
    },
    {
      "ante": 2,
      "blind_type": "SMALL",
      "event_type": "blind_result",
      "data": {
        "score": 1127,
        "required": 800,
        "success": true,
        "margin": 327,
        "margin_pct": 40.9,
        "hands_used": 2,
        "discards_used": 1,
        "best_hand": "FULL_HOUSE",
        "close_call": false
      },
      "timestamp": 10
    },
    {
      "ante": 2,
      "blind_type": null,
      "event_type": "joker_acquired",
      "data": {
        "joker": "Smiley Face",
        "source": "shop"
      },
      "timestamp": 11
    },
    {
      "ante": 2,
      "blind_type": null,
      "event_type": "shop_visit",
      "data": {
        "jokers_bought": [
          "Smiley Face"
        ],
        "planets_used": [],
        "money_spent": 4,
        "money_remaining": 1
      },
      "timestamp": 12
    },
    {
      "ante": 2,
      "blind_type": "BIG",
      "event_type": "blind_result",
      "data": {
        "score": 1540,
        "required": 1200,
        "success": true,
        "margin": 340,
        "margin_pct": 28.3,
        "hands_used": 2,
        "discards_used": 2,
        "best_hand": "FLUSH",
        "close_call": false
      },
      "timestamp": 13
    },
    {
      "ante": 2,
      "blind_type": null,
      "event_type": "joker_acquired",
      "data": {
        "joker": "Showman",
        "source": "shop"
      },
      "timestamp": 14
    },
    {
      "ante": 2,
      "blind_type": null,
      "event_type": "shop_visit",
      "data": {
        "jokers_bought": [
          "Showman"
        ],
        "planets_used": [],
        "money_spent": 5,
        "money_remaining": 0
      },
      "timestamp": 15
    },
    {
      "ante": 2,
      "blind_type": "BOSS",
      "event_type": "blind_result",
      "data": {
        "score": 4212,
        "required": 2400,
        "success": true,
        "margin": 1812,
        "margin_pct": 75.5,
        "hands_used": 2,
        "discards_used": 1,
        "best_hand": "TWO_PAIR",
        "close_call": false,
        "boss_name": "The Wall"
      },
      "timestamp": 16
    },
    {
      "ante": 2,
      "blind_type": null,
      "event_type": "hand_level_up",
      "data": {
        "planet": "Neptune",
        "hand_type": "STRAIGHT_FLUSH",
        "new_level": 2
      },
      "timestamp": 17
    },
    {
      "ante": 2,
      "blind_type": null,
      "event_type": "shop_visit",
      "data": {
        "jokers_bought": [],
        "planets_used": [
          "Neptune"
        ],
        "money_spent": 3,
        "money_remaining": 2
      },
      "timestamp": 18
    },
    {
      "ante": 3,
      "blind_type": "SMALL",
      "event_type": "blind_result",
      "data": {
        "score": 2212,
        "required": 2000,
        "success": true,
        "margin": 212,
        "margin_pct": 10.6,
        "hands_used": 3,
        "discards_used": 3,
        "best_hand": "TWO_PAIR",
        "close_call": true
      },
      "timestamp": 19
    },
    {
      "ante": 3,
      "blind_type": null,
      "event_type": "shop_visit",
      "data": {
        "jokers_bought": [],
        "planets_used": [],
        "money_spent": 0,
        "money_remaining": 5
      },
      "timestamp": 20
    },
    {
      "ante": 3,
      "blind_type": "BIG",
      "event_type": "blind_result",
      "data": {
        "score": 3046,
        "required": 3000,
        "success": true,
        "margin": 46,
        "margin_pct": 1.5,
        "hands_used": 4,
        "discards_used": 1,
        "best_hand": "TWO_PAIR",
        "close_call": true
      },
      "timestamp": 21
    },
    {
      "ante": 3,
      "blind_type": null,
      "event_type": "hand_level_up",
      "data": {
        "planet": "Planet X",
        "hand_type": "FIVE_OF_A_KIND",
        "new_level": 2
      },
      "timestamp": 22
    },
    {
      "ante": 3,
      "blind_type": null,
      "event_type": "shop_visit",
      "data": {
        "jokers_bought": [],
        "planets_used": [
          "Planet X"
        ],
        "money_spent": 3,
        "money_remaining": 7
      },
      "timestamp": 23
    },
    {
      "ante": 3,
      "blind_type": "BOSS",
      "event_type": "blind_result",
      "data": {
        "score": 1823,
        "required": 6000,
        "success": false,
        "margin": -4177,
        "margin_pct": -69.6,
        "hands_used": 4,
        "discards_used": 2,
        "best_hand": "TWO_PAIR",
        "close_call": false,
        "boss_name": "The Wall"
      },
      "timestamp": 24
    },
    {
      "ante": 3,
      "blind_type": "BOSS",
      "event_type": "run_end",
      "data": {
        "victory": false,
        "blinds_beaten": 8,
        "final_money": 7,
        "final_jokers": [
          "Golden Ticket",
          "Abstract Joker",
          "Shoot the Moon",
          "Smiley Face",
          "Showman"
        ],
        "final_hand_levels": {
          "STRAIGHT_FLUSH": 2,
          "FIVE_OF_A_KIND": 2
        }
      },
      "timestamp": 25
    }
  ],
  "summary": {
    "total_blinds_attempted": 9,
    "blinds_won": 8,
    "close_calls": 4,
    "jokers_acquired": 5,
    "planets_used": 2,
    "victory": false
  }
}